{
    "KPlugin": {
        "Authors": [
            {
                "Email": "vl@fidra.de",
                "Name": "Volker Lanz"
            }
        ],
        "Category": "BackendPlugin",
        "Description": "The LibParted backend for KDE Partition Manager",
        "Description[ar]": "سند LibParted ل‍«مدير كدي للأقسام»",
        "Description[ast]": "El backend LibParted pal xestor KDE de particiones",
        "Description[bg]": "Ядро LibParted за управление на дялове в KDE",
        "Description[bs]": "Pozadina Libparteda za KDE‑ov menadžer particija",
        "Description[ca@valencia]": "Un dorsal pel LibParted del gestor de particions del KDE",
        "Description[ca]": "Un dorsal pel LibParted del gestor de particions del KDE",
        "Description[cs]": "Podpůrná vrstva LibParted pro správce diskových oddílů pro KDE",
        "Description[da]": "LibParted-backend til KDE partitionshåndtering",
        "Description[de]": "Das LibParted-Backend für die KDE-Partitionsverwaltung",
        "Description[el]": "Το σύστημα υποστήριξης LibParted για τον διαχειριστή κατατμήσεων του KDE",
        "Description[en_GB]": "The LibParted backend for KDE Partition Manager",
        "Description[es]": "El motor LibParted para el gestor de particiones de KDE",
        "Description[et]": "KDE partitsioonihalduri LibPartedi taustaprogramm",
        "Description[fi]": "KDE:n osionhallinnan LibParted-taustaosa",
        "Description[fr]": "Le moteur LibParted pour le gestionnaire de partitions de KDE",
        "Description[gl]": "A infraestrutura LibParted para o xestor de particións de KDE",
        "Description[hu]": "LibParted háttérprogram a KDE partíciószerkesztőhöz",
        "Description[id]": "Backend LibParted untuk Manajer Partisi KDE",
        "Description[it]": "Il motore LibParted del gestore delle partizioni di KDE",
        "Description[ko]": "KDE 파티션 관리자를 위한 LibParted 백엔드",
        "Description[lt]": "LibParted galinė sąsaja KDE skaidinių tvarkyklei",
        "Description[mr]": "केडीई विभाजन व्यवस्थापक करिता लिबपार्टेड बॅकएन्ड",
        "Description[nb]": "LibParted bakgrunnsmogtoren for KDE partisjonsbehandler.",
        "Description[nds]": "Dat LibParted-Hülpprogramm för KDE-Partitschonenpleger",
        "Description[nl]": "De LibParted-backend voor de KDE-partitiebeheerder",
        "Description[pa]": "ਕੇਡੀਈ ਪਾਰਟੀਸ਼ਨ ਮੈਨੇਜਰ ਲਈ LibParted ਬੈਕਐਂਡ",
        "Description[pl]": "Silnik LibParted dla zarządzania partycjami",
        "Description[pt]": "A infra-estrutura da LibParted para o Gestor de Partições do KDE",
        "Description[pt_BR]": "Uma infraestrutura LibParted para o gerenciador de partições do KDE",
        "Description[ro]": "Platforma LibParted pentru Gestionarul de partiții KDE",
        "Description[ru]": "Механизм LibParted для диспетчера разделов для KDE",
        "Description[sk]": "LibParted - program v pozadí pre KDE Správcu partícií",
        "Description[sl]": "Zaledje LibParted za upravljalnik razdelkov za KDE",
        "Description[sr@ijekavian]": "Позадина Либпартеда за КДЕ‑ов менаџер партиција",
        "Description[sr@ijekavianlatin]": "Pozadina LibParteda za KDE‑ov menadžer particija",
        "Description[sr@latin]": "Pozadina LibParteda za KDE‑ov menadžer particija",
        "Description[sr]": "Позадина Либпартеда за КДЕ‑ов менаџер партиција",
        "Description[sv]": "LibParted bakgrundsprogram för KDE:s partitionshanterare",
        "Description[tr]": "KDE Disk Bölümü Yöneticisi LibParted arka ucu",
        "Description[ug]": "KDE رايون باشقۇرغۇچنىڭ LibParted ئارقا ئۇچى",
        "Description[uk]": "Сервер LibParted для Керування розділами KDE",
        "Description[x-test]": "xxThe LibParted backend for KDE Partition Managerxx",
        "Description[zh_CN]": "KDE 分区管理器的 LibParted 后端",
        "Description[zh_TW]": "KDE 磁碟分割區管理員的 LibParted 後端介面",
        "EnabledByDefault": true,
        "Icon": "preferences-plugin",
        "Id": "pmlibpartedbackendplugin",
        "License": "GPL",
        "Name": "KDE Partition Manager LibParted Backend",
        "Name[ar]": "سند LibParted ل‍«مدير كدي للأقسام»",
        "Name[ast]": "Backend LibParted del xestor KDE de particiones",
        "Name[bg]": "Ядро LibParted за управление на дялове в KDE",
        "Name[bs]": "LibParted pozadina  za KDE‑ov menadžer particija",
        "Name[ca@valencia]": "Dorsal pel LibParted del gestor de particions del KDE",
        "Name[ca]": "Dorsal pel LibParted del gestor de particions del KDE",
        "Name[cs]": "Podpůrná vrstva LibParted pro správce diskových oddílů pro KDE",
        "Name[da]": "LibParted-backend til KDE partitionshåndtering",
        "Name[de]": "KDE-Partitionsverwaltung LibParted-Backend",
        "Name[el]": "Σύστημα υποστήριξης LibParted για τον διαχειριστή κατατμήσεων του KDE",
        "Name[en_GB]": "KDE Partition Manager LibParted Backend",
        "Name[es]": "Motor LibParted para el gestor de particiones de KDE",
        "Name[et]": "KDE partitsioonihalduri LibPartedi taustaprogramm",
        "Name[fi]": "KDE:n osionhallinnan LibParted-taustaosa",
        "Name[fr]": "Moteur LibParted pour le gestionnaire de partitions de KDE",
        "Name[gl]": "Infraestrutura LibParted para o xestor de particións de KDE",
        "Name[hu]": "KDE partíciószerkesztő LibParted háttérprogram",
        "Name[id]": "Backend LibParted Manajer Parisi KDE",
        "Name[it]": "Motore LibParted del gestore delle partizioni di KDE",
        "Name[ko]": "KDE 파티션 관리자 LibParted 백엔드",
        "Name[lt]": "KDE skaidinių tvarkyklės LibParted galinė sąsaja",
        "Name[mr]": "केडीई विभाजन व्यवस्थापक लिबपार्टेड बॅकएन्ड",
        "Name[nb]": "KDE partisjonsbehandler, bakgrunnsmotor for libparted",
        "Name[nds]": "LibParted-Hülpprogramm för KDE-Partitschonenpleger",
        "Name[nl]": "KDE-partitiebeheerder LibParted-backend",
        "Name[pa]": "ਕੇਡੀਈ ਪਾਰਟੀਸ਼ਨ ਮੈਨੇਜਰ LibParted ਬੈਕਐਂਡ",
        "Name[pl]": "Silnik LibParted zarządzania partycjami",
        "Name[pt]": "Infra-Estrutura da LibParted para o Gestor de Partições do KDE",
        "Name[pt_BR]": "Infraestrutura LibParted do gerenciador de partições do KDE",
        "Name[ro]": "Platformă LibParted pentru Gestionarul de partiții KDE",
        "Name[ru]": "Механизм LibParted",
        "Name[sk]": "LibParted - program v pozadí pre KDE Správcu partícií",
        "Name[sl]": "Zaledje LibParted za upravljalnik razdelkov za KDE",
        "Name[sr@ijekavian]": "Позадина Либпартеда за КДЕ‑ов менаџер партиција",
        "Name[sr@ijekavianlatin]": "Pozadina LibParteda za KDE‑ov menadžer particija",
        "Name[sr@latin]": "Pozadina LibParteda za KDE‑ov menadžer particija",
        "Name[sr]": "Позадина Либпартеда за КДЕ‑ов менаџер партиција",
        "Name[sv]": "KDE:s partitionshanterare LibParted bakgrundsprogram",
        "Name[tr]": "KDE Disk Bölümü Yöneticisi LibParted arka ucu",
        "Name[ug]": "KDE رايون باشقۇرغۇچنىڭ LibParted ئارقا ئۇچى",
        "Name[uk]": "Сервер LibParted Керування розділами KDE",
        "Name[x-test]": "xxKDE Partition Manager LibParted Backendxx",
        "Name[zh_CN]": "KDE 分区管理器 LibParted 后端",
        "Name[zh_TW]": "KDE 磁碟分割區管理員 LibParted 後端介面",
        "ServiceTypes": [
            "PartitionManager/Plugin"
        ],
        "Version": "1",
        "Website": "http://www.partitionmanager.org"
    }
}
